Metadata-Version: 1.0
Name: tabelog-scraper
Version: 1.3
Summary: 食べログのスクレイピング
Home-page: https://github.com/koboriakira/tabelog_scraper
Author: Kobori Akira
Author-email: private.beats@gmail.com
License: MIT
Platform: UNKNOWN
